{"202":{"0":{"temoti":{"waza":[{"id":"68","val":"100.0"},{"id":"243","val":"98.7"},{"id":"204","val":"66.2"},{"id":"227","val":"58.9"},{"id":"194","val":"35.1"},{"id":"219","val":"20.5"},{"id":"133","val":"19.2"}],"tokusei":[{"id":"23","val":"100.0"}],"motimono":[{"id":"158","val":"47.6"},{"id":"159","val":"25.6"},{"id":"234","val":"17.1"},{"id":"198","val":"4.9"},{"id":"640","val":"1.2"},{"id":"219","val":"1.2"},{"id":"540","val":"1.2"},{"id":"275","val":"1.2"}],"pokemon":[{"id":468,"form":0},{"id":887,"form":0},{"id":687,"form":0},{"id":131,"form":0},{"id":778,"form":0},{"id":815,"form":0},{"id":547,"form":0},{"id":94,"form":0},{"id":727,"form":0},{"id":59,"form":0}]},"lose":{"waza":[{"id":"157","val":"9.4"},{"id":"242","val":"6.3"},{"id":"566","val":"6.3"},{"id":"330","val":"6.3"},{"id":"304","val":"6.3"},{"id":"518","val":"3.1"},{"id":"675","val":"3.1"},{"id":"323","val":"3.1"},{"id":"12","val":"3.1"},{"id":"165","val":"3.1"}],"pokemon":[{"id":248,"form":0},{"id":887,"form":0},{"id":700,"form":0},{"id":530,"form":0},{"id":727,"form":0},{"id":815,"form":0},{"id":350,"form":0},{"id":598,"form":0},{"id":324,"form":0},{"id":279,"form":0}]},"win":{"waza":[{"id":"243","val":"61.1"},{"id":"68","val":"38.9"}],"pokemon":[{"id":130,"form":0},{"id":468,"form":0},{"id":324,"form":0},{"id":849,"form":0},{"id":815,"form":0},{"id":876,"form":1},{"id":812,"form":0},{"id":589,"form":0},{"id":479,"form":2},{"id":780,"form":0}]}}},"208":{"0":{"temoti":{"waza":[{"id":"776","val":"77.4"},{"id":"442","val":"42.7"},{"id":"89","val":"36.9"},{"id":"182","val":"30.0"},{"id":"667","val":"25.9"},{"id":"157","val":"25.2"},{"id":"360","val":"22.2"},{"id":"706","val":"21.3"},{"id":"334","val":"19.5"},{"id":"484","val":"16.8"}],"tokusei":[{"id":"5","val":"64.8"},{"id":"125","val":"18.6"},{"id":"69","val":"16.6"}],"motimono":[{"id":"640","val":"29.3"},{"id":"639","val":"21.9"},{"id":"234","val":"14.4"},{"id":"220","val":"12.1"},{"id":"270","val":"7.3"},{"id":"687","val":"4.1"},{"id":"1122","val":"2.5"},{"id":"542","val":"1.7"},{"id":"291","val":"1.7"},{"id":"266","val":"1.2"}],"pokemon":[{"id":356,"form":0},{"id":706,"form":0},{"id":59,"form":0},{"id":130,"form":0},{"id":468,"form":0},{"id":423,"form":0},{"id":861,"form":0},{"id":350,"form":0},{"id":727,"form":0},{"id":628,"form":0}]},"lose":{"waza":[{"id":"257","val":"9.7"},{"id":"56","val":"8.9"},{"id":"667","val":"6.0"},{"id":"330","val":"4.6"},{"id":"605","val":"3.5"},{"id":"89","val":"3.5"},{"id":"780","val":"2.9"},{"id":"394","val":"2.7"},{"id":"414","val":"2.7"},{"id":"370","val":"2.6"}],"pokemon":[{"id":468,"form":0},{"id":815,"form":0},{"id":350,"form":0},{"id":131,"form":0},{"id":464,"form":0},{"id":730,"form":0},{"id":479,"form":2},{"id":887,"form":0},{"id":324,"form":0},{"id":812,"form":0}]},"win":{"waza":[{"id":"776","val":"28.3"},{"id":"442","val":"16.6"},{"id":"89","val":"13.8"},{"id":"667","val":"7.3"},{"id":"360","val":"7.0"},{"id":"798","val":"6.7"},{"id":"484","val":"5.1"},{"id":"157","val":"4.7"},{"id":"457","val":"3.4"},{"id":"529","val":"3.4"}],"pokemon":[{"id":248,"form":0},{"id":468,"form":0},{"id":547,"form":0},{"id":815,"form":0},{"id":530,"form":0},{"id":876,"form":1},{"id":778,"form":0},{"id":887,"form":0},{"id":131,"form":0},{"id":884,"form":0}]}}},"211":{"0":{"temoti":{"waza":[{"id":"86","val":"60.8"},{"id":"398","val":"53.6"},{"id":"453","val":"52.8"},{"id":"491","val":"47.8"},{"id":"269","val":"32.1"},{"id":"179","val":"26.0"},{"id":"127","val":"24.2"},{"id":"710","val":"22.8"},{"id":"182","val":"8.0"},{"id":"196","val":"7.8"}],"tokusei":[{"id":"22","val":"55.0"},{"id":"33","val":"45.0"}],"motimono":[{"id":"275","val":"64.2"},{"id":"191","val":"7.9"},{"id":"640","val":"5.9"},{"id":"281","val":"4.6"},{"id":"547","val":"4.2"},{"id":"541","val":"2.2"},{"id":"287","val":"2.0"},{"id":"650","val":"1.7"},{"id":"157","val":"1.1"},{"id":"234","val":"1.1"}],"pokemon":[{"id":279,"form":0},{"id":272,"form":0},{"id":730,"form":0},{"id":847,"form":0},{"id":834,"form":0},{"id":530,"form":0},{"id":839,"form":0},{"id":609,"form":0},{"id":628,"form":0},{"id":812,"form":0}]},"lose":{"waza":[{"id":"85","val":"7.0"},{"id":"89","val":"5.5"},{"id":"157","val":"5.2"},{"id":"667","val":"4.9"},{"id":"340","val":"3.0"},{"id":"87","val":"3.0"},{"id":"412","val":"2.7"},{"id":"403","val":"2.7"},{"id":"414","val":"2.4"},{"id":"566","val":"2.4"}],"pokemon":[{"id":887,"form":0},{"id":530,"form":0},{"id":815,"form":0},{"id":730,"form":0},{"id":812,"form":0},{"id":248,"form":0},{"id":131,"form":0},{"id":479,"form":2},{"id":350,"form":0},{"id":143,"form":0}]},"win":{"waza":[{"id":"398","val":"35.8"},{"id":"127","val":"19.3"},{"id":"453","val":"17.6"},{"id":"710","val":"10.8"},{"id":"491","val":"7.4"},{"id":"179","val":"6.3"},{"id":"675","val":"0.6"},{"id":"57","val":"0.6"},{"id":"196","val":"0.6"},{"id":"340","val":"0.6"}],"pokemon":[{"id":547,"form":0},{"id":815,"form":0},{"id":468,"form":0},{"id":861,"form":0},{"id":530,"form":0},{"id":248,"form":0},{"id":730,"form":0},{"id":884,"form":0},{"id":887,"form":0},{"id":35,"form":0}]}}},"213":{"0":{"temoti":{"waza":[{"id":"157","val":"48.9"},{"id":"379","val":"44.4"},{"id":"471","val":"40.1"},{"id":"92","val":"32.8"},{"id":"182","val":"30.5"},{"id":"89","val":"25.3"},{"id":"360","val":"23.3"},{"id":"611","val":"22.7"},{"id":"504","val":"18.3"},{"id":"470","val":"16.9"}],"tokusei":[{"id":"5","val":"61.0"},{"id":"126","val":"36.1"},{"id":"82","val":"2.9"}],"motimono":[{"id":"217","val":"20.6"},{"id":"234","val":"20.4"},{"id":"639","val":"10.8"},{"id":"219","val":"7.1"},{"id":"276","val":"6.4"},{"id":"157","val":"5.2"},{"id":"150","val":"5.1"},{"id":"162","val":"4.6"},{"id":"315","val":"3.9"},{"id":"160","val":"3.2"}],"pokemon":[{"id":356,"form":0},{"id":876,"form":1},{"id":530,"form":0},{"id":248,"form":0},{"id":131,"form":0},{"id":778,"form":0},{"id":324,"form":0},{"id":700,"form":0},{"id":818,"form":0},{"id":701,"form":0}]},"lose":{"waza":[{"id":"442","val":"11.5"},{"id":"157","val":"11.2"},{"id":"56","val":"4.9"},{"id":"605","val":"3.7"},{"id":"304","val":"3.2"},{"id":"101","val":"3.2"},{"id":"330","val":"2.9"},{"id":"585","val":"2.7"},{"id":"257","val":"2.4"},{"id":"755","val":"2.2"}],"pokemon":[{"id":530,"form":0},{"id":815,"form":0},{"id":248,"form":0},{"id":464,"form":0},{"id":730,"form":0},{"id":356,"form":0},{"id":131,"form":0},{"id":350,"form":0},{"id":887,"form":0},{"id":547,"form":0}]},"win":{"waza":[{"id":"157","val":"73.6"},{"id":"89","val":"12.6"},{"id":"360","val":"3.8"},{"id":"414","val":"3.1"},{"id":"444","val":"2.5"},{"id":"450","val":"1.9"},{"id":"282","val":"1.9"},{"id":"611","val":"0.6"}],"pokemon":[{"id":468,"form":0},{"id":547,"form":0},{"id":356,"form":0},{"id":815,"form":0},{"id":3,"form":0},{"id":6,"form":0},{"id":876,"form":1},{"id":727,"form":0},{"id":479,"form":2},{"id":59,"form":0}]}}},"215":{"0":{"temoti":{"waza":[{"id":"252","val":"80.1"},{"id":"196","val":"53.7"},{"id":"269","val":"48.7"},{"id":"420","val":"45.9"},{"id":"103","val":"44.8"},{"id":"57","val":"36.6"},{"id":"313","val":"21.1"},{"id":"556","val":"16.8"},{"id":"675","val":"8.8"},{"id":"492","val":"7.8"}],"tokusei":[{"id":"39","val":"99.3"},{"id":"124","val":"0.7"}],"motimono":[{"id":"538","val":"59.0"},{"id":"275","val":"26.1"},{"id":"201","val":"4.3"},{"id":"287","val":"4.0"},{"id":"265","val":"2.6"},{"id":"206","val":"1.8"},{"id":"221","val":"1.4"},{"id":"268","val":"0.7"}],"pokemon":[{"id":468,"form":0},{"id":839,"form":0},{"id":547,"form":0},{"id":815,"form":0},{"id":730,"form":0},{"id":861,"form":0},{"id":530,"form":0},{"id":324,"form":0},{"id":3,"form":0},{"id":812,"form":0}]},"lose":{"waza":[{"id":"605","val":"8.0"},{"id":"157","val":"7.5"},{"id":"442","val":"6.8"},{"id":"585","val":"5.9"},{"id":"257","val":"5.2"},{"id":"394","val":"4.5"},{"id":"136","val":"3.2"},{"id":"409","val":"2.1"},{"id":"340","val":"2.1"},{"id":"85","val":"2.0"}],"pokemon":[{"id":815,"form":0},{"id":468,"form":0},{"id":530,"form":0},{"id":727,"form":0},{"id":59,"form":0},{"id":547,"form":0},{"id":248,"form":0},{"id":887,"form":0},{"id":324,"form":0},{"id":730,"form":0}]},"win":{"waza":[{"id":"420","val":"27.0"},{"id":"556","val":"25.5"},{"id":"196","val":"14.6"},{"id":"675","val":"10.9"},{"id":"813","val":"8.8"},{"id":"492","val":"2.9"},{"id":"57","val":"2.9"},{"id":"8","val":"2.2"},{"id":"252","val":"2.2"},{"id":"280","val":"1.5"}],"pokemon":[{"id":468,"form":0},{"id":547,"form":0},{"id":887,"form":0},{"id":3,"form":0},{"id":876,"form":1},{"id":131,"form":0},{"id":609,"form":0},{"id":812,"form":0},{"id":130,"form":0},{"id":815,"form":0}]}}},"220":{"0":{"temoti":{"waza":[{"id":"33","val":"100.0"},{"id":"181","val":"100.0"},{"id":"175","val":"100.0"},{"id":"89","val":"100.0"}],"tokusei":[],"motimono":[],"pokemon":[{"id":547,"form":0},{"id":818,"form":0},{"id":876,"form":1},{"id":38,"form":1},{"id":342,"form":0}]},"lose":{"waza":[],"pokemon":[]},"win":{"waza":[],"pokemon":[]}}},"221":{"0":{"temoti":{"waza":[{"id":"556","val":"100.0"},{"id":"420","val":"66.7"},{"id":"89","val":"60.0"},{"id":"182","val":"60.0"},{"id":"667","val":"40.0"},{"id":"133","val":"33.3"},{"id":"276","val":"33.3"},{"id":"157","val":"6.7"}],"tokusei":[{"id":"47","val":"100.0"}],"motimono":[{"id":"538","val":"91.7"},{"id":"220","val":"8.3"}],"pokemon":[{"id":766,"form":0},{"id":812,"form":0},{"id":59,"form":0},{"id":678,"form":0},{"id":468,"form":0},{"id":579,"form":0},{"id":510,"form":0},{"id":195,"form":0},{"id":727,"form":0},{"id":876,"form":1}]},"lose":{"waza":[{"id":"430","val":"25.0"},{"id":"664","val":"12.5"},{"id":"403","val":"12.5"},{"id":"53","val":"12.5"},{"id":"745","val":"12.5"},{"id":"605","val":"12.5"},{"id":"751","val":"12.5"}],"pokemon":[{"id":884,"form":0},{"id":468,"form":0},{"id":609,"form":0},{"id":730,"form":0},{"id":887,"form":0},{"id":818,"form":0}]},"win":{"waza":[{"id":"556","val":"50.0"},{"id":"420","val":"33.3"},{"id":"89","val":"16.7"}],"pokemon":[{"id":468,"form":0},{"id":510,"form":0},{"id":628,"form":0},{"id":356,"form":0},{"id":248,"form":0}]}}},"222":{"0":{"temoti":{"waza":[{"id":"457","val":"100.0"},{"id":"710","val":"100.0"},{"id":"120","val":"63.6"},{"id":"157","val":"63.6"},{"id":"89","val":"27.9"},{"id":"182","val":"20.7"},{"id":"333","val":"18.6"},{"id":"675","val":"5.7"}],"tokusei":[{"id":"55","val":"100.0"}],"motimono":[{"id":"276","val":"71.0"},{"id":"639","val":"17.2"},{"id":"270","val":"5.4"},{"id":"158","val":"4.3"},{"id":"268","val":"2.2"}],"pokemon":[{"id":9,"form":0},{"id":197,"form":0},{"id":471,"form":0},{"id":575,"form":0},{"id":38,"form":1},{"id":468,"form":0},{"id":887,"form":0},{"id":547,"form":0},{"id":864,"form":0},{"id":876,"form":1}]},"lose":{"waza":[{"id":"85","val":"14.6"},{"id":"667","val":"12.5"},{"id":"136","val":"8.3"},{"id":"76","val":"8.3"},{"id":"89","val":"6.3"},{"id":"452","val":"6.3"},{"id":"157","val":"6.3"},{"id":"409","val":"4.2"},{"id":"605","val":"4.2"},{"id":"573","val":"4.2"}],"pokemon":[{"id":530,"form":0},{"id":815,"form":0},{"id":479,"form":2},{"id":812,"form":0},{"id":687,"form":0},{"id":534,"form":0},{"id":839,"form":0},{"id":598,"form":0},{"id":131,"form":0},{"id":38,"form":0}]},"win":{"waza":[{"id":"457","val":"46.2"},{"id":"710","val":"30.8"},{"id":"157","val":"16.9"},{"id":"89","val":"4.6"},{"id":"675","val":"1.5"}],"pokemon":[{"id":468,"form":0},{"id":530,"form":0},{"id":727,"form":0},{"id":356,"form":0},{"id":131,"form":0},{"id":324,"form":0},{"id":534,"form":0},{"id":730,"form":0},{"id":3,"form":0},{"id":609,"form":0}]}},"1":{"temoti":{"waza":[{"id":"668","val":"99.6"},{"id":"261","val":"90.2"},{"id":"101","val":"77.9"},{"id":"243","val":"23.3"},{"id":"446","val":"19.8"},{"id":"182","val":"13.7"},{"id":"133","val":"10.9"},{"id":"506","val":"10.1"},{"id":"174","val":"9.0"},{"id":"250","val":"7.3"}],"tokusei":[{"id":"130","val":"99.7"},{"id":"133","val":"0.3"}],"motimono":[{"id":"538","val":"99.5"},{"id":"234","val":"0.2"},{"id":"296","val":"0.1"},{"id":"217","val":"0.1"},{"id":"238","val":"0.0"}],"pokemon":[{"id":547,"form":0},{"id":815,"form":0},{"id":887,"form":0},{"id":131,"form":0},{"id":248,"form":0},{"id":861,"form":0},{"id":778,"form":0},{"id":350,"form":0},{"id":423,"form":0},{"id":530,"form":0}]},"lose":{"waza":[{"id":"242","val":"8.0"},{"id":"247","val":"5.2"},{"id":"566","val":"5.2"},{"id":"605","val":"4.3"},{"id":"399","val":"3.9"},{"id":"56","val":"3.5"},{"id":"389","val":"3.4"},{"id":"282","val":"3.4"},{"id":"585","val":"3.1"},{"id":"442","val":"3.0"}],"pokemon":[{"id":248,"form":0},{"id":887,"form":0},{"id":815,"form":0},{"id":812,"form":0},{"id":468,"form":0},{"id":730,"form":0},{"id":131,"form":0},{"id":727,"form":0},{"id":884,"form":0},{"id":479,"form":2}]},"win":{"waza":[{"id":"101","val":"80.3"},{"id":"243","val":"6.8"},{"id":"506","val":"4.0"},{"id":"247","val":"2.5"},{"id":"408","val":"1.8"},{"id":"202","val":"1.5"},{"id":"250","val":"1.1"},{"id":"196","val":"0.9"},{"id":"503","val":"0.6"},{"id":"58","val":"0.3"}],"pokemon":[{"id":356,"form":0},{"id":815,"form":0},{"id":468,"form":0},{"id":547,"form":0},{"id":131,"form":0},{"id":530,"form":0},{"id":730,"form":0},{"id":858,"form":0},{"id":324,"form":0},{"id":3,"form":0}]}}},"224":{"0":{"temoti":{"waza":[{"id":"323","val":"85.7"},{"id":"412","val":"82.3"},{"id":"182","val":"59.4"},{"id":"58","val":"57.3"},{"id":"53","val":"37.9"},{"id":"503","val":"10.7"},{"id":"56","val":"8.8"},{"id":"57","val":"7.1"},{"id":"94","val":"6.8"},{"id":"126","val":"6.1"}],"tokusei":[{"id":"97","val":"47.4"},{"id":"141","val":"29.6"},{"id":"21","val":"23.0"}],"motimono":[{"id":"297","val":"27.7"},{"id":"232","val":"21.8"},{"id":"278","val":"13.5"},{"id":"234","val":"10.1"},{"id":"268","val":"9.5"},{"id":"326","val":"5.1"},{"id":"243","val":"3.4"},{"id":"254","val":"2.3"},{"id":"639","val":"1.5"},{"id":"1122","val":"1.1"}],"pokemon":[{"id":858,"form":0},{"id":468,"form":0},{"id":876,"form":1},{"id":356,"form":0},{"id":510,"form":0},{"id":534,"form":0},{"id":324,"form":0},{"id":6,"form":0},{"id":279,"form":0},{"id":815,"form":0}]},"lose":{"waza":[{"id":"412","val":"7.2"},{"id":"85","val":"6.7"},{"id":"157","val":"6.3"},{"id":"452","val":"5.8"},{"id":"605","val":"5.3"},{"id":"438","val":"4.3"},{"id":"202","val":"3.8"},{"id":"585","val":"3.4"},{"id":"136","val":"2.9"},{"id":"87","val":"2.4"}],"pokemon":[{"id":730,"form":0},{"id":812,"form":0},{"id":815,"form":0},{"id":3,"form":0},{"id":778,"form":0},{"id":858,"form":0},{"id":248,"form":0},{"id":131,"form":0},{"id":534,"form":0},{"id":468,"form":0}]},"win":{"waza":[{"id":"323","val":"68.2"},{"id":"412","val":"11.6"},{"id":"58","val":"7.1"},{"id":"53","val":"3.9"},{"id":"503","val":"3.4"},{"id":"57","val":"1.3"},{"id":"331","val":"1.1"},{"id":"188","val":"1.1"},{"id":"56","val":"1.1"},{"id":"430","val":"0.5"}],"pokemon":[{"id":468,"form":0},{"id":815,"form":0},{"id":547,"form":0},{"id":530,"form":0},{"id":730,"form":0},{"id":887,"form":0},{"id":248,"form":0},{"id":727,"form":0},{"id":59,"form":0},{"id":812,"form":0}]}}},"225":{"0":{"temoti":{"waza":[{"id":"252","val":"59.6"},{"id":"413","val":"48.9"},{"id":"573","val":"40.4"},{"id":"196","val":"39.4"},{"id":"194","val":"34.0"},{"id":"333","val":"30.9"},{"id":"211","val":"28.7"},{"id":"182","val":"28.7"},{"id":"280","val":"22.3"},{"id":"270","val":"17.0"}],"tokusei":[{"id":"55","val":"53.2"},{"id":"72","val":"46.8"}],"motimono":[{"id":"270","val":"53.2"},{"id":"275","val":"35.5"},{"id":"219","val":"11.3"}],"pokemon":[{"id":875,"form":0},{"id":887,"form":0},{"id":547,"form":0},{"id":628,"form":0},{"id":36,"form":0},{"id":777,"form":0},{"id":882,"form":0},{"id":598,"form":0},{"id":815,"form":0},{"id":279,"form":0}]},"lose":{"waza":[{"id":"257","val":"16.3"},{"id":"157","val":"7.0"},{"id":"605","val":"7.0"},{"id":"780","val":"7.0"},{"id":"585","val":"4.7"},{"id":"394","val":"4.7"},{"id":"85","val":"4.7"},{"id":"442","val":"4.7"},{"id":"786","val":"2.3"},{"id":"59","val":"2.3"}],"pokemon":[{"id":815,"form":0},{"id":468,"form":0},{"id":59,"form":0},{"id":38,"form":0},{"id":876,"form":1},{"id":555,"form":2},{"id":547,"form":0},{"id":530,"form":0},{"id":884,"form":0},{"id":858,"form":0}]},"win":{"waza":[{"id":"413","val":"45.8"},{"id":"333","val":"20.8"},{"id":"196","val":"12.5"},{"id":"573","val":"12.5"},{"id":"211","val":"4.2"},{"id":"813","val":"4.2"}],"pokemon":[{"id":547,"form":0},{"id":468,"form":0},{"id":887,"form":0},{"id":135,"form":0},{"id":815,"form":0},{"id":727,"form":0},{"id":356,"form":0},{"id":812,"form":0},{"id":609,"form":0},{"id":709,"form":0}]}}},"226":{"0":{"temoti":{"waza":[{"id":"542","val":"75.9"},{"id":"366","val":"68.5"},{"id":"56","val":"52.8"},{"id":"58","val":"39.4"},{"id":"182","val":"31.1"},{"id":"503","val":"26.4"},{"id":"403","val":"19.5"},{"id":"57","val":"16.5"},{"id":"59","val":"16.3"},{"id":"355","val":"14.5"}],"tokusei":[{"id":"33","val":"85.0"},{"id":"11","val":"14.5"},{"id":"41","val":"0.5"}],"motimono":[{"id":"270","val":"65.3"},{"id":"234","val":"7.8"},{"id":"186","val":"7.3"},{"id":"650","val":"6.0"},{"id":"195","val":"3.1"},{"id":"157","val":"2.9"},{"id":"158","val":"2.7"},{"id":"640","val":"2.3"},{"id":"243","val":"0.9"},{"id":"267","val":"0.5"}],"pokemon":[{"id":678,"form":0},{"id":730,"form":0},{"id":464,"form":0},{"id":356,"form":0},{"id":778,"form":0},{"id":468,"form":0},{"id":26,"form":0},{"id":784,"form":0},{"id":279,"form":0},{"id":35,"form":0}]},"lose":{"waza":[{"id":"157","val":"14.7"},{"id":"85","val":"12.0"},{"id":"87","val":"4.1"},{"id":"340","val":"3.9"},{"id":"605","val":"3.7"},{"id":"9","val":"3.5"},{"id":"566","val":"2.7"},{"id":"803","val":"2.7"},{"id":"403","val":"2.5"},{"id":"452","val":"2.5"}],"pokemon":[{"id":248,"form":0},{"id":812,"form":0},{"id":131,"form":0},{"id":479,"form":2},{"id":887,"form":0},{"id":815,"form":0},{"id":730,"form":0},{"id":530,"form":0},{"id":468,"form":0},{"id":464,"form":0}]},"win":{"waza":[{"id":"542","val":"41.5"},{"id":"56","val":"37.2"},{"id":"503","val":"5.5"},{"id":"58","val":"4.7"},{"id":"403","val":"4.0"},{"id":"57","val":"3.7"},{"id":"59","val":"2.9"},{"id":"196","val":"0.6"}],"pokemon":[{"id":468,"form":0},{"id":815,"form":0},{"id":812,"form":0},{"id":547,"form":0},{"id":530,"form":0},{"id":3,"form":0},{"id":727,"form":0},{"id":248,"form":0},{"id":876,"form":1},{"id":356,"form":0}]}}},"236":{"0":{"temoti":{"waza":[{"id":"270","val":"100.0"},{"id":"418","val":"100.0"},{"id":"182","val":"100.0"},{"id":"168","val":"100.0"}],"tokusei":[{"id":"72","val":"100.0"}],"motimono":[{"id":"270","val":"100.0"}],"pokemon":[{"id":861,"form":0},{"id":35,"form":0},{"id":530,"form":0},{"id":479,"form":2},{"id":812,"form":0}]},"lose":{"waza":[{"id":"605","val":"100.0"}],"pokemon":[{"id":468,"form":0}]},"win":{"waza":[],"pokemon":[]}}},"237":{"0":{"temoti":{"waza":[{"id":"252","val":"96.4"},{"id":"370","val":"85.6"},{"id":"418","val":"38.4"},{"id":"270","val":"37.8"},{"id":"389","val":"36.9"},{"id":"469","val":"31.6"},{"id":"183","val":"22.7"},{"id":"197","val":"7.4"},{"id":"280","val":"7.1"},{"id":"157","val":"5.6"}],"tokusei":[{"id":"22","val":"95.4"},{"id":"101","val":"4.6"},{"id":"80","val":"0.0"}],"motimono":[{"id":"547","val":"32.7"},{"id":"158","val":"13.1"},{"id":"640","val":"11.9"},{"id":"686","val":"11.3"},{"id":"1119","val":"7.3"},{"id":"241","val":"4.6"},{"id":"192","val":"3.8"},{"id":"159","val":"2.4"},{"id":"268","val":"1.9"},{"id":"214","val":"1.7"}],"pokemon":[{"id":468,"form":0},{"id":815,"form":0},{"id":547,"form":0},{"id":887,"form":0},{"id":598,"form":0},{"id":248,"form":0},{"id":530,"form":0},{"id":812,"form":0},{"id":131,"form":0},{"id":279,"form":0}]},"lose":{"waza":[{"id":"340","val":"9.6"},{"id":"605","val":"7.5"},{"id":"585","val":"6.7"},{"id":"403","val":"6.4"},{"id":"442","val":"3.1"},{"id":"304","val":"2.9"},{"id":"94","val":"2.7"},{"id":"257","val":"2.7"},{"id":"413","val":"2.4"},{"id":"19","val":"2.2"}],"pokemon":[{"id":815,"form":0},{"id":468,"form":0},{"id":887,"form":0},{"id":730,"form":0},{"id":547,"form":0},{"id":530,"form":0},{"id":131,"form":0},{"id":812,"form":0},{"id":6,"form":0},{"id":700,"form":0}]},"win":{"waza":[{"id":"370","val":"48.9"},{"id":"418","val":"13.6"},{"id":"183","val":"11.4"},{"id":"389","val":"10.3"},{"id":"252","val":"6.6"},{"id":"280","val":"3.2"},{"id":"364","val":"1.3"},{"id":"157","val":"1.1"},{"id":"813","val":"1.0"},{"id":"444","val":"0.6"}],"pokemon":[{"id":248,"form":0},{"id":530,"form":0},{"id":815,"form":0},{"id":131,"form":0},{"id":727,"form":0},{"id":547,"form":0},{"id":468,"form":0},{"id":884,"form":0},{"id":887,"form":0},{"id":812,"form":0}]}}},"246":{"0":{"temoti":{"waza":[{"id":"174","val":"100.0"},{"id":"43","val":"100.0"},{"id":"246","val":"100.0"},{"id":"23","val":"100.0"}],"tokusei":[],"motimono":[],"pokemon":[{"id":468,"form":0},{"id":222,"form":1},{"id":876,"form":1},{"id":464,"form":0},{"id":356,"form":0}]},"lose":{"waza":[],"pokemon":[]},"win":{"waza":[],"pokemon":[]}}},"248":{"0":{"temoti":{"waza":[{"id":"157","val":"94.2"},{"id":"182","val":"74.9"},{"id":"242","val":"68.1"},{"id":"276","val":"61.3"},{"id":"808","val":"13.9"},{"id":"372","val":"11.4"},{"id":"7","val":"9.5"},{"id":"89","val":"9.1"},{"id":"667","val":"7.9"},{"id":"442","val":"7.5"}],"tokusei":[{"id":"45","val":"99.3"},{"id":"127","val":"0.7"}],"motimono":[{"id":"639","val":"66.3"},{"id":"275","val":"10.9"},{"id":"220","val":"6.2"},{"id":"640","val":"4.0"},{"id":"270","val":"3.4"},{"id":"157","val":"2.8"},{"id":"287","val":"1.8"},{"id":"189","val":"1.1"},{"id":"159","val":"0.6"},{"id":"268","val":"0.4"}],"pokemon":[{"id":468,"form":0},{"id":530,"form":0},{"id":887,"form":0},{"id":356,"form":0},{"id":815,"form":0},{"id":547,"form":0},{"id":727,"form":0},{"id":812,"form":0},{"id":479,"form":2},{"id":59,"form":0}]},"lose":{"waza":[{"id":"442","val":"7.9"},{"id":"136","val":"6.7"},{"id":"276","val":"5.8"},{"id":"605","val":"5.8"},{"id":"370","val":"5.4"},{"id":"56","val":"4.3"},{"id":"89","val":"3.8"},{"id":"409","val":"3.7"},{"id":"667","val":"3.5"},{"id":"776","val":"3.4"}],"pokemon":[{"id":815,"form":0},{"id":812,"form":0},{"id":534,"form":0},{"id":248,"form":0},{"id":530,"form":0},{"id":464,"form":0},{"id":730,"form":0},{"id":468,"form":0},{"id":3,"form":0},{"id":882,"form":0}]},"win":{"waza":[{"id":"157","val":"55.5"},{"id":"242","val":"16.8"},{"id":"276","val":"9.8"},{"id":"808","val":"3.9"},{"id":"372","val":"2.3"},{"id":"444","val":"2.0"},{"id":"89","val":"1.7"},{"id":"667","val":"1.6"},{"id":"442","val":"1.6"},{"id":"7","val":"1.0"}],"pokemon":[{"id":468,"form":0},{"id":356,"form":0},{"id":887,"form":0},{"id":815,"form":0},{"id":876,"form":1},{"id":131,"form":0},{"id":248,"form":0},{"id":727,"form":0},{"id":547,"form":0},{"id":324,"form":0}]}}},"263":{"0":{"temoti":{"waza":[{"id":"182","val":"100.0"},{"id":"263","val":"100.0"},{"id":"187","val":"100.0"},{"id":"245","val":"100.0"}],"tokusei":[{"id":"82","val":"100.0"}],"motimono":[{"id":"158","val":"100.0"}],"pokemon":[{"id":11,"form":0},{"id":624,"form":0},{"id":129,"form":0},{"id":175,"form":0},{"id":509,"form":0}]},"lose":{"waza":[{"id":"284","val":"33.3"},{"id":"75","val":"33.3"},{"id":"776","val":"33.3"}],"pokemon":[{"id":812,"form":0},{"id":598,"form":0},{"id":324,"form":0}]},"win":{"waza":[{"id":"245","val":"100.0"}],"pokemon":[{"id":818,"form":0},{"id":700,"form":0}]}}},"264":{"0":{"temoti":{"waza":[{"id":"245","val":"96.1"},{"id":"187","val":"93.5"},{"id":"707","val":"72.7"},{"id":"182","val":"67.5"},{"id":"231","val":"20.8"},{"id":"91","val":"18.2"},{"id":"583","val":"7.8"},{"id":"402","val":"5.2"},{"id":"514","val":"5.2"},{"id":"441","val":"5.2"}],"tokusei":[{"id":"82","val":"96.4"},{"id":"95","val":"3.6"}],"motimono":[{"id":"159","val":"82.1"},{"id":"163","val":"7.1"},{"id":"158","val":"3.6"},{"id":"273","val":"3.6"},{"id":"162","val":"3.6"}],"pokemon":[{"id":35,"form":0},{"id":812,"form":0},{"id":130,"form":0},{"id":625,"form":0},{"id":727,"form":0},{"id":131,"form":0},{"id":876,"form":1},{"id":778,"form":0},{"id":556,"form":0},{"id":815,"form":0}]},"lose":{"waza":[{"id":"442","val":"14.3"},{"id":"136","val":"14.3"},{"id":"157","val":"9.5"},{"id":"605","val":"4.8"},{"id":"710","val":"4.8"},{"id":"409","val":"4.8"},{"id":"490","val":"4.8"},{"id":"56","val":"4.8"},{"id":"492","val":"4.8"},{"id":"583","val":"4.8"}],"pokemon":[{"id":815,"form":0},{"id":248,"form":0},{"id":625,"form":0},{"id":880,"form":0},{"id":818,"form":0},{"id":131,"form":0},{"id":778,"form":0},{"id":324,"form":0},{"id":468,"form":0},{"id":614,"form":0}]},"win":{"waza":[{"id":"245","val":"78.6"},{"id":"707","val":"14.3"},{"id":"231","val":"7.1"}],"pokemon":[{"id":812,"form":0},{"id":479,"form":2},{"id":815,"form":0},{"id":35,"form":0},{"id":25,"form":0},{"id":248,"form":0},{"id":706,"form":0},{"id":279,"form":0},{"id":464,"form":0},{"id":861,"form":0}]}},"1":{"temoti":{"waza":[{"id":"57","val":"90.5"},{"id":"575","val":"81.0"},{"id":"196","val":"57.1"},{"id":"415","val":"52.4"},{"id":"282","val":"42.9"},{"id":"86","val":"33.3"},{"id":"270","val":"14.3"},{"id":"33","val":"4.8"},{"id":"68","val":"4.8"},{"id":"122","val":"4.8"}],"tokusei":[{"id":"82","val":"52.9"},{"id":"95","val":"41.2"},{"id":"53","val":"5.9"}],"motimono":[{"id":"287","val":"52.9"},{"id":"538","val":"29.4"},{"id":"275","val":"17.6"}],"pokemon":[{"id":839,"form":0},{"id":815,"form":0},{"id":861,"form":0},{"id":849,"form":1},{"id":423,"form":0},{"id":275,"form":0},{"id":38,"form":0},{"id":623,"form":0},{"id":841,"form":0},{"id":882,"form":0}]},"lose":{"waza":[{"id":"252","val":"8.3"},{"id":"369","val":"8.3"},{"id":"751","val":"8.3"},{"id":"136","val":"8.3"},{"id":"585","val":"8.3"},{"id":"276","val":"8.3"},{"id":"157","val":"8.3"},{"id":"304","val":"8.3"},{"id":"605","val":"8.3"},{"id":"490","val":"8.3"}],"pokemon":[{"id":815,"form":0},{"id":812,"form":0},{"id":248,"form":0},{"id":547,"form":0},{"id":534,"form":0},{"id":874,"form":0},{"id":700,"form":0},{"id":468,"form":0},{"id":887,"form":0}]},"win":{"waza":[{"id":"196","val":"100.0"}],"pokemon":[{"id":94,"form":0}]}}},"271":{"0":{"temoti":{"waza":[{"id":"310","val":"100.0"},{"id":"72","val":"100.0"},{"id":"55","val":"100.0"},{"id":"61","val":"100.0"}],"tokusei":[{"id":"33","val":"100.0"}],"motimono":[],"pokemon":[{"id":823,"form":0},{"id":448,"form":0},{"id":815,"form":0}]},"lose":{"waza":[],"pokemon":[]},"win":{"waza":[],"pokemon":[]}}},"272":{"0":{"temoti":{"waza":[{"id":"58","val":"71.9"},{"id":"252","val":"59.4"},{"id":"412","val":"48.9"},{"id":"182","val":"36.2"},{"id":"330","val":"33.2"},{"id":"202","val":"31.6"},{"id":"503","val":"29.5"},{"id":"56","val":"28.9"},{"id":"437","val":"19.9"},{"id":"59","val":"10.6"}],"tokusei":[{"id":"33","val":"93.6"},{"id":"44","val":"6.1"},{"id":"20","val":"0.3"}],"motimono":[{"id":"270","val":"29.5"},{"id":"640","val":"26.7"},{"id":"639","val":"16.7"},{"id":"268","val":"8.9"},{"id":"545","val":"3.4"},{"id":"243","val":"2.3"},{"id":"275","val":"1.6"},{"id":"254","val":"1.5"},{"id":"234","val":"1.4"},{"id":"297","val":"1.3"}],"pokemon":[{"id":279,"form":0},{"id":468,"form":0},{"id":887,"form":0},{"id":131,"form":0},{"id":598,"form":0},{"id":530,"form":0},{"id":815,"form":0},{"id":847,"form":0},{"id":547,"form":0},{"id":884,"form":0}]},"lose":{"waza":[{"id":"340","val":"10.1"},{"id":"403","val":"8.5"},{"id":"157","val":"5.8"},{"id":"188","val":"4.4"},{"id":"573","val":"3.7"},{"id":"413","val":"3.7"},{"id":"19","val":"3.3"},{"id":"605","val":"3.1"},{"id":"585","val":"2.5"},{"id":"452","val":"2.2"}],"pokemon":[{"id":815,"form":0},{"id":468,"form":0},{"id":887,"form":0},{"id":248,"form":0},{"id":812,"form":0},{"id":131,"form":0},{"id":3,"form":0},{"id":130,"form":0},{"id":6,"form":0},{"id":534,"form":0}]},"win":{"waza":[{"id":"330","val":"17.1"},{"id":"56","val":"17.0"},{"id":"58","val":"13.8"},{"id":"412","val":"13.6"},{"id":"503","val":"11.2"},{"id":"202","val":"8.7"},{"id":"437","val":"6.4"},{"id":"57","val":"5.2"},{"id":"59","val":"3.1"},{"id":"252","val":"1.5"}],"pokemon":[{"id":468,"form":0},{"id":815,"form":0},{"id":547,"form":0},{"id":248,"form":0},{"id":479,"form":2},{"id":530,"form":0},{"id":887,"form":0},{"id":131,"form":0},{"id":730,"form":0},{"id":350,"form":0}]}}},"273":{"0":{"temoti":{"waza":[{"id":"182","val":"100.0"},{"id":"153","val":"100.0"},{"id":"389","val":"100.0"},{"id":"72","val":"100.0"}],"tokusei":[{"id":"48","val":"100.0"}],"motimono":[{"id":"564","val":"100.0"}],"pokemon":[{"id":79,"form":1},{"id":349,"form":0},{"id":324,"form":0},{"id":143,"form":0},{"id":129,"form":0}]},"lose":{"waza":[{"id":"188","val":"50.0"},{"id":"257","val":"50.0"}],"pokemon":[{"id":537,"form":0},{"id":38,"form":0}]},"win":{"waza":[],"pokemon":[]}}},"274":{"0":{"temoti":{"waza":[{"id":"153","val":"50.0"},{"id":"310","val":"50.0"},{"id":"371","val":"50.0"},{"id":"389","val":"50.0"},{"id":"205","val":"50.0"},{"id":"33","val":"50.0"},{"id":"182","val":"50.0"},{"id":"72","val":"50.0"}],"tokusei":[{"id":"48","val":"100.0"}],"motimono":[{"id":"564","val":"100.0"}],"pokemon":[{"id":849,"form":0},{"id":324,"form":0},{"id":349,"form":0},{"id":812,"form":0},{"id":815,"form":0},{"id":861,"form":0},{"id":129,"form":0},{"id":882,"form":0},{"id":143,"form":0},{"id":79,"form":1}]},"lose":{"waza":[],"pokemon":[]},"win":{"waza":[],"pokemon":[]}}},"275":{"0":{"temoti":{"waza":[{"id":"252","val":"49.7"},{"id":"348","val":"41.7"},{"id":"257","val":"37.4"},{"id":"157","val":"32.8"},{"id":"399","val":"32.0"},{"id":"389","val":"22.8"},{"id":"669","val":"19.1"},{"id":"437","val":"18.1"},{"id":"412","val":"16.4"},{"id":"182","val":"13.6"}],"tokusei":[{"id":"34","val":"99.3"},{"id":"124","val":"0.7"}],"motimono":[{"id":"270","val":"36.0"},{"id":"275","val":"24.3"},{"id":"267","val":"6.8"},{"id":"268","val":"6.5"},{"id":"220","val":"4.9"},{"id":"326","val":"3.6"},{"id":"639","val":"3.3"},{"id":"640","val":"2.9"},{"id":"251","val":"2.7"},{"id":"232","val":"2.1"}],"pokemon":[{"id":324,"form":0},{"id":6,"form":0},{"id":38,"form":0},{"id":547,"form":0},{"id":887,"form":0},{"id":815,"form":0},{"id":356,"form":0},{"id":468,"form":0},{"id":464,"form":0},{"id":248,"form":0}]},"lose":{"waza":[{"id":"340","val":"7.6"},{"id":"257","val":"6.3"},{"id":"605","val":"4.9"},{"id":"585","val":"4.7"},{"id":"403","val":"4.7"},{"id":"157","val":"4.7"},{"id":"394","val":"4.3"},{"id":"780","val":"4.1"},{"id":"188","val":"3.7"},{"id":"53","val":"3.1"}],"pokemon":[{"id":815,"form":0},{"id":468,"form":0},{"id":59,"form":0},{"id":248,"form":0},{"id":887,"form":0},{"id":324,"form":0},{"id":131,"form":0},{"id":727,"form":0},{"id":547,"form":0},{"id":700,"form":0}]},"win":{"waza":[{"id":"257","val":"15.7"},{"id":"348","val":"15.1"},{"id":"399","val":"11.7"},{"id":"669","val":"8.4"},{"id":"157","val":"6.0"},{"id":"389","val":"5.4"},{"id":"492","val":"5.4"},{"id":"437","val":"4.2"},{"id":"412","val":"3.9"},{"id":"400","val":"3.6"}],"pokemon":[{"id":887,"form":0},{"id":815,"form":0},{"id":730,"form":0},{"id":356,"form":0},{"id":547,"form":0},{"id":530,"form":0},{"id":468,"form":0},{"id":876,"form":1},{"id":350,"form":0},{"id":818,"form":0}]}}},"279":{"0":{"temoti":{"waza":[{"id":"542","val":"98.1"},{"id":"366","val":"75.2"},{"id":"503","val":"64.6"},{"id":"182","val":"63.2"},{"id":"56","val":"17.2"},{"id":"57","val":"14.6"},{"id":"369","val":"13.6"},{"id":"58","val":"13.3"},{"id":"469","val":"7.1"},{"id":"355","val":"6.2"}],"tokusei":[{"id":"2","val":"100.0"}],"motimono":[{"id":"275","val":"58.5"},{"id":"285","val":"12.8"},{"id":"287","val":"6.9"},{"id":"195","val":"3.7"},{"id":"158","val":"2.3"},{"id":"270","val":"2.3"},{"id":"297","val":"2.1"},{"id":"547","val":"1.8"},{"id":"162","val":"1.2"},{"id":"243","val":"1.1"}],"pokemon":[{"id":272,"form":0},{"id":468,"form":0},{"id":834,"form":0},{"id":598,"form":0},{"id":887,"form":0},{"id":131,"form":0},{"id":135,"form":0},{"id":847,"form":0},{"id":812,"form":0},{"id":237,"form":0}]},"lose":{"waza":[{"id":"157","val":"11.4"},{"id":"85","val":"8.6"},{"id":"605","val":"6.1"},{"id":"585","val":"4.3"},{"id":"340","val":"2.9"},{"id":"403","val":"2.9"},{"id":"304","val":"2.8"},{"id":"573","val":"2.4"},{"id":"87","val":"2.2"},{"id":"797","val":"2.1"}],"pokemon":[{"id":248,"form":0},{"id":468,"form":0},{"id":887,"form":0},{"id":815,"form":0},{"id":131,"form":0},{"id":812,"form":0},{"id":479,"form":2},{"id":730,"form":0},{"id":884,"form":0},{"id":547,"form":0}]},"win":{"waza":[{"id":"542","val":"52.6"},{"id":"503","val":"29.2"},{"id":"57","val":"6.9"},{"id":"56","val":"5.3"},{"id":"311","val":"2.3"},{"id":"58","val":"1.2"},{"id":"369","val":"0.6"},{"id":"196","val":"0.5"},{"id":"362","val":"0.5"},{"id":"98","val":"0.5"}],"pokemon":[{"id":547,"form":0},{"id":812,"form":0},{"id":815,"form":0},{"id":468,"form":0},{"id":3,"form":0},{"id":530,"form":0},{"id":534,"form":0},{"id":356,"form":0},{"id":887,"form":0},{"id":248,"form":0}]}}},"280":{"0":{"temoti":{"waza":[{"id":"270","val":"100.0"},{"id":"425","val":"100.0"},{"id":"502","val":"100.0"},{"id":"433","val":"100.0"}],"tokusei":[{"id":"36","val":"100.0"}],"motimono":[{"id":"275","val":"100.0"}],"pokemon":[{"id":887,"form":0},{"id":598,"form":0},{"id":778,"form":0},{"id":350,"form":0},{"id":59,"form":0}]},"lose":{"waza":[{"id":"252","val":"33.3"},{"id":"57","val":"33.3"},{"id":"157","val":"33.3"}],"pokemon":[{"id":812,"form":0},{"id":248,"form":0},{"id":25,"form":0}]},"win":{"waza":[],"pokemon":[]}}},"282":{"0":{"temoti":{"waza":[{"id":"605","val":"51.8"},{"id":"433","val":"48.2"},{"id":"585","val":"47.7"},{"id":"94","val":"36.8"},{"id":"286","val":"31.5"},{"id":"595","val":"30.2"},{"id":"85","val":"20.8"},{"id":"797","val":"20.0"},{"id":"425","val":"19.7"},{"id":"412","val":"17.3"}],"tokusei":[{"id":"36","val":"67.9"},{"id":"140","val":"22.6"},{"id":"28","val":"9.5"}],"motimono":[{"id":"275","val":"36.1"},{"id":"287","val":"20.7"},{"id":"640","val":"6.9"},{"id":"270","val":"6.2"},{"id":"297","val":"5.8"},{"id":"158","val":"4.5"},{"id":"199","val":"3.6"},{"id":"644","val":"3.1"},{"id":"162","val":"2.1"},{"id":"253","val":"1.2"}],"pokemon":[{"id":887,"form":0},{"id":815,"form":0},{"id":547,"form":0},{"id":350,"form":0},{"id":468,"form":0},{"id":248,"form":0},{"id":812,"form":0},{"id":59,"form":0},{"id":876,"form":1},{"id":727,"form":0}]},"lose":{"waza":[{"id":"442","val":"12.5"},{"id":"157","val":"5.1"},{"id":"605","val":"4.7"},{"id":"566","val":"4.2"},{"id":"430","val":"3.5"},{"id":"257","val":"3.2"},{"id":"188","val":"3.1"},{"id":"247","val":"3.0"},{"id":"304","val":"2.5"},{"id":"56","val":"2.2"}],"pokemon":[{"id":815,"form":0},{"id":530,"form":0},{"id":887,"form":0},{"id":248,"form":0},{"id":812,"form":0},{"id":468,"form":0},{"id":884,"form":0},{"id":131,"form":0},{"id":730,"form":0},{"id":324,"form":0}]},"win":{"waza":[{"id":"605","val":"30.7"},{"id":"585","val":"24.5"},{"id":"797","val":"17.3"},{"id":"94","val":"9.2"},{"id":"595","val":"4.6"},{"id":"85","val":"4.5"},{"id":"412","val":"2.8"},{"id":"425","val":"2.5"},{"id":"247","val":"1.2"},{"id":"473","val":"1.0"}],"pokemon":[{"id":547,"form":0},{"id":468,"form":0},{"id":887,"form":0},{"id":815,"form":0},{"id":861,"form":0},{"id":876,"form":1},{"id":356,"form":0},{"id":3,"form":0},{"id":534,"form":0},{"id":248,"form":0}]}}},"290":{"0":{"temoti":{"waza":[{"id":"232","val":"100.0"},{"id":"189","val":"100.0"},{"id":"10","val":"100.0"},{"id":"71","val":"100.0"}],"tokusei":[{"id":"14","val":"100.0"}],"motimono":[],"pokemon":[{"id":362,"form":0},{"id":163,"form":0},{"id":109,"form":0}]},"lose":{"waza":[{"id":"157","val":"100.0"}],"pokemon":[{"id":248,"form":0}]},"win":{"waza":[],"pokemon":[]}}},"291":{"0":{"temoti":{"waza":[{"id":"226","val":"70.1"},{"id":"14","val":"55.1"},{"id":"182","val":"46.3"},{"id":"512","val":"37.4"},{"id":"141","val":"34.7"},{"id":"91","val":"27.2"},{"id":"164","val":"14.3"},{"id":"71","val":"13.6"},{"id":"496","val":"13.6"},{"id":"404","val":"12.2"}],"tokusei":[{"id":"3","val":"100.0"}],"motimono":[{"id":"275","val":"64.9"},{"id":"639","val":"6.8"},{"id":"195","val":"6.8"},{"id":"158","val":"5.4"},{"id":"234","val":"4.1"},{"id":"207","val":"2.7"},{"id":"270","val":"1.4"},{"id":"230","val":"1.4"}],"pokemon":[{"id":876,"form":1},{"id":248,"form":0},{"id":700,"form":0},{"id":454,"form":0},{"id":818,"form":0},{"id":861,"form":0},{"id":780,"form":0},{"id":730,"form":0},{"id":847,"form":0},{"id":461,"form":0}]},"lose":{"waza":[{"id":"157","val":"16.3"},{"id":"340","val":"10.2"},{"id":"754","val":"6.1"},{"id":"19","val":"4.1"},{"id":"789","val":"4.1"},{"id":"304","val":"4.1"},{"id":"585","val":"4.1"},{"id":"53","val":"4.1"},{"id":"59","val":"4.1"},{"id":"583","val":"2.0"}],"pokemon":[{"id":887,"form":0},{"id":815,"form":0},{"id":248,"form":0},{"id":839,"form":0},{"id":861,"form":0},{"id":464,"form":0},{"id":884,"form":0},{"id":880,"form":0},{"id":752,"form":0},{"id":730,"form":0}]},"win":{"waza":[{"id":"512","val":"44.4"},{"id":"404","val":"22.2"},{"id":"91","val":"22.2"},{"id":"141","val":"11.1"}],"pokemon":[{"id":849,"form":0},{"id":876,"form":1},{"id":815,"form":0},{"id":3,"form":0},{"id":880,"form":0},{"id":812,"form":0},{"id":763,"form":0},{"id":555,"form":2},{"id":131,"form":0}]}}},"292":{"0":{"temoti":{"waza":[{"id":"502","val":"85.9"},{"id":"425","val":"71.5"},{"id":"261","val":"56.3"},{"id":"203","val":"41.8"},{"id":"421","val":"32.0"},{"id":"182","val":"23.3"},{"id":"404","val":"19.0"},{"id":"141","val":"18.0"},{"id":"247","val":"10.9"},{"id":"566","val":"8.9"}],"tokusei":[{"id":"25","val":"100.0"}],"motimono":[{"id":"650","val":"94.3"},{"id":"275","val":"5.0"},{"id":"1123","val":"0.4"}],"pokemon":[{"id":818,"form":0},{"id":547,"form":0},{"id":464,"form":0},{"id":882,"form":0},{"id":880,"form":0},{"id":468,"form":0},{"id":887,"form":0},{"id":530,"form":0},{"id":131,"form":0},{"id":555,"form":2}]},"lose":{"waza":[{"id":"157","val":"12.4"},{"id":"257","val":"6.4"},{"id":"282","val":"6.4"},{"id":"595","val":"5.6"},{"id":"389","val":"5.2"},{"id":"403","val":"4.9"},{"id":"425","val":"4.1"},{"id":"101","val":"4.1"},{"id":"340","val":"3.7"},{"id":"780","val":"3.7"}],"pokemon":[{"id":815,"form":0},{"id":468,"form":0},{"id":812,"form":0},{"id":530,"form":0},{"id":356,"form":0},{"id":887,"form":0},{"id":778,"form":0},{"id":479,"form":2},{"id":248,"form":0},{"id":727,"form":0}]},"win":{"waza":[{"id":"425","val":"46.9"},{"id":"247","val":"14.3"},{"id":"421","val":"14.3"},{"id":"404","val":"13.3"},{"id":"141","val":"7.1"},{"id":"450","val":"2.0"},{"id":"405","val":"1.0"},{"id":"566","val":"1.0"}],"pokemon":[{"id":876,"form":1},{"id":547,"form":0},{"id":815,"form":0},{"id":887,"form":0},{"id":730,"form":0},{"id":94,"form":0},{"id":812,"form":0},{"id":248,"form":0},{"id":356,"form":0},{"id":858,"form":0}]}}},"302":{"0":{"temoti":{"waza":[{"id":"511","val":"90.6"},{"id":"252","val":"49.3"},{"id":"261","val":"36.7"},{"id":"269","val":"34.8"},{"id":"502","val":"30.6"},{"id":"271","val":"28.5"},{"id":"492","val":"25.7"},{"id":"241","val":"25.3"},{"id":"425","val":"22.1"},{"id":"240","val":"18.4"}],"tokusei":[{"id":"158","val":"100.0"},{"id":"51","val":"0.0"},{"id":"100","val":"0.0"}],"motimono":[{"id":"686","val":"39.1"},{"id":"547","val":"24.2"},{"id":"158","val":"8.5"},{"id":"275","val":"8.4"},{"id":"279","val":"5.5"},{"id":"278","val":"2.4"},{"id":"234","val":"2.2"},{"id":"219","val":"1.8"},{"id":"265","val":"1.2"},{"id":"162","val":"1.0"}],"pokemon":[{"id":468,"form":0},{"id":815,"form":0},{"id":6,"form":0},{"id":887,"form":0},{"id":3,"form":0},{"id":812,"form":0},{"id":534,"form":0},{"id":530,"form":0},{"id":324,"form":0},{"id":547,"form":0}]},"lose":{"waza":[{"id":"605","val":"12.5"},{"id":"585","val":"8.5"},{"id":"157","val":"5.3"},{"id":"257","val":"3.8"},{"id":"442","val":"3.7"},{"id":"304","val":"3.5"},{"id":"340","val":"3.2"},{"id":"583","val":"2.6"},{"id":"780","val":"2.3"},{"id":"56","val":"2.3"}],"pokemon":[{"id":468,"form":0},{"id":815,"form":0},{"id":547,"form":0},{"id":730,"form":0},{"id":887,"form":0},{"id":248,"form":0},{"id":131,"form":0},{"id":812,"form":0},{"id":778,"form":0},{"id":700,"form":0}]},"win":{"waza":[{"id":"492","val":"45.1"},{"id":"425","val":"30.0"},{"id":"282","val":"12.9"},{"id":"252","val":"5.5"},{"id":"555","val":"2.9"},{"id":"101","val":"2.0"},{"id":"389","val":"0.8"},{"id":"165","val":"0.3"},{"id":"371","val":"0.2"},{"id":"247","val":"0.1"}],"pokemon":[{"id":887,"form":0},{"id":815,"form":0},{"id":547,"form":0},{"id":876,"form":1},{"id":356,"form":0},{"id":530,"form":0},{"id":812,"form":0},{"id":468,"form":0},{"id":609,"form":0},{"id":94,"form":0}]}}},"303":{"0":{"temoti":{"waza":[{"id":"583","val":"78.4"},{"id":"442","val":"78.1"},{"id":"389","val":"61.2"},{"id":"182","val":"32.7"},{"id":"270","val":"29.7"},{"id":"157","val":"29.0"},{"id":"269","val":"27.3"},{"id":"424","val":"17.1"},{"id":"196","val":"11.7"},{"id":"242","val":"5.9"}],"tokusei":[{"id":"22","val":"43.7"},{"id":"125","val":"39.6"},{"id":"52","val":"16.7"}],"motimono":[{"id":"270","val":"29.7"},{"id":"639","val":"26.3"},{"id":"275","val":"15.2"},{"id":"191","val":"7.1"},{"id":"220","val":"4.3"},{"id":"158","val":"4.0"},{"id":"184","val":"4.0"},{"id":"540","val":"2.8"},{"id":"234","val":"1.5"},{"id":"547","val":"1.2"}],"pokemon":[{"id":324,"form":0},{"id":727,"form":0},{"id":468,"form":0},{"id":812,"form":0},{"id":3,"form":0},{"id":464,"form":0},{"id":356,"form":0},{"id":858,"form":0},{"id":6,"form":0},{"id":700,"form":0}]},"lose":{"waza":[{"id":"257","val":"12.3"},{"id":"780","val":"7.5"},{"id":"394","val":"7.5"},{"id":"667","val":"4.8"},{"id":"89","val":"4.3"},{"id":"304","val":"3.7"},{"id":"430","val":"3.2"},{"id":"595","val":"3.2"},{"id":"56","val":"3.2"},{"id":"566","val":"3.2"}],"pokemon":[{"id":815,"form":0},{"id":468,"form":0},{"id":730,"form":0},{"id":59,"form":0},{"id":727,"form":0},{"id":530,"form":0},{"id":887,"form":0},{"id":700,"form":0},{"id":884,"form":0},{"id":609,"form":0}]},"win":{"waza":[{"id":"442","val":"37.8"},{"id":"583","val":"28.0"},{"id":"157","val":"18.9"},{"id":"389","val":"9.8"},{"id":"9","val":"2.4"},{"id":"424","val":"1.8"},{"id":"196","val":"0.6"},{"id":"242","val":"0.6"}],"pokemon":[{"id":468,"form":0},{"id":815,"form":0},{"id":887,"form":0},{"id":547,"form":0},{"id":730,"form":0},{"id":248,"form":0},{"id":778,"form":0},{"id":6,"form":0},{"id":700,"form":0},{"id":534,"form":0}]}}},"310":{"0":{"temoti":{"waza":[{"id":"555","val":"60.8"},{"id":"53","val":"52.1"},{"id":"182","val":"44.6"},{"id":"521","val":"43.7"},{"id":"87","val":"43.2"},{"id":"85","val":"42.8"},{"id":"315","val":"35.8"},{"id":"415","val":"14.5"},{"id":"86","val":"9.7"},{"id":"598","val":"8.1"}],"tokusei":[{"id":"31","val":"94.1"},{"id":"58","val":"4.5"},{"id":"9","val":"1.3"}],"motimono":[{"id":"287","val":"16.5"},{"id":"275","val":"16.0"},{"id":"541","val":"14.9"},{"id":"297","val":"14.5"},{"id":"270","val":"11.6"},{"id":"242","val":"7.9"},{"id":"1118","val":"4.7"},{"id":"640","val":"2.4"},{"id":"1119","val":"1.9"},{"id":"158","val":"1.7"}],"pokemon":[{"id":130,"form":0},{"id":279,"form":0},{"id":547,"form":0},{"id":272,"form":0},{"id":468,"form":0},{"id":884,"form":0},{"id":887,"form":0},{"id":812,"form":0},{"id":727,"form":0},{"id":861,"form":0}]},"lose":{"waza":[{"id":"667","val":"5.5"},{"id":"89","val":"5.2"},{"id":"157","val":"4.6"},{"id":"56","val":"4.2"},{"id":"605","val":"3.9"},{"id":"257","val":"3.6"},{"id":"585","val":"2.9"},{"id":"414","val":"2.7"},{"id":"780","val":"2.5"},{"id":"566","val":"2.5"}],"pokemon":[{"id":815,"form":0},{"id":887,"form":0},{"id":131,"form":0},{"id":812,"form":0},{"id":530,"form":0},{"id":248,"form":0},{"id":884,"form":0},{"id":880,"form":0},{"id":479,"form":2},{"id":468,"form":0}]},"win":{"waza":[{"id":"87","val":"24.0"},{"id":"85","val":"22.8"},{"id":"53","val":"15.7"},{"id":"555","val":"12.9"},{"id":"315","val":"9.1"},{"id":"521","val":"5.8"},{"id":"435","val":"4.7"},{"id":"304","val":"2.0"},{"id":"98","val":"1.2"},{"id":"804","val":"0.9"}],"pokemon":[{"id":468,"form":0},{"id":547,"form":0},{"id":131,"form":0},{"id":815,"form":0},{"id":530,"form":0},{"id":812,"form":0},{"id":598,"form":0},{"id":887,"form":0},{"id":876,"form":1},{"id":6,"form":0}]}}},"320":{"0":{"temoti":{"waza":[{"id":"58","val":"100.0"},{"id":"323","val":"100.0"},{"id":"56","val":"100.0"},{"id":"304","val":"100.0"}],"tokusei":[{"id":"41","val":"100.0"}],"motimono":[{"id":"297","val":"100.0"}],"pokemon":[{"id":627,"form":0},{"id":25,"form":0},{"id":813,"form":0},{"id":35,"form":0},{"id":66,"form":0},{"id":509,"form":0}]},"lose":{"waza":[{"id":"438","val":"7.7"},{"id":"94","val":"7.7"},{"id":"605","val":"7.7"},{"id":"85","val":"7.7"},{"id":"434","val":"3.8"},{"id":"542","val":"3.8"},{"id":"778","val":"3.8"},{"id":"566","val":"3.8"},{"id":"202","val":"3.8"},{"id":"389","val":"3.8"}],"pokemon":[{"id":815,"form":0},{"id":876,"form":1},{"id":130,"form":0},{"id":887,"form":0},{"id":778,"form":0},{"id":530,"form":0},{"id":528,"form":0},{"id":464,"form":0},{"id":324,"form":0},{"id":6,"form":0}]},"win":{"waza":[{"id":"323","val":"90.0"},{"id":"56","val":"10.0"}],"pokemon":[{"id":464,"form":0},{"id":12,"form":0},{"id":839,"form":0},{"id":448,"form":0},{"id":858,"form":0},{"id":727,"form":0},{"id":35,"form":0},{"id":59,"form":0},{"id":750,"form":0},{"id":530,"form":0}]}}},"321":{"0":{"temoti":{"waza":[{"id":"323","val":"91.9"},{"id":"56","val":"41.1"},{"id":"90","val":"34.1"},{"id":"156","val":"30.8"},{"id":"182","val":"28.1"},{"id":"196","val":"23.8"},{"id":"58","val":"20.5"},{"id":"57","val":"18.4"},{"id":"59","val":"17.8"},{"id":"487","val":"15.7"}],"tokusei":[{"id":"41","val":"48.3"},{"id":"12","val":"27.6"},{"id":"46","val":"24.1"}],"motimono":[{"id":"297","val":"60.5"},{"id":"150","val":"22.2"},{"id":"287","val":"6.1"},{"id":"243","val":"1.9"},{"id":"234","val":"1.9"},{"id":"268","val":"1.5"},{"id":"882","val":"1.1"},{"id":"640","val":"1.1"},{"id":"564","val":"1.1"},{"id":"275","val":"0.8"}],"pokemon":[{"id":279,"form":0},{"id":25,"form":0},{"id":887,"form":0},{"id":143,"form":0},{"id":678,"form":0},{"id":36,"form":0},{"id":555,"form":0},{"id":660,"form":0},{"id":778,"form":0},{"id":763,"form":0}]},"lose":{"waza":[{"id":"85","val":"11.8"},{"id":"438","val":"6.6"},{"id":"87","val":"5.9"},{"id":"452","val":"5.1"},{"id":"412","val":"5.1"},{"id":"9","val":"3.7"},{"id":"157","val":"3.7"},{"id":"437","val":"2.9"},{"id":"94","val":"2.9"},{"id":"778","val":"2.9"}],"pokemon":[{"id":812,"form":0},{"id":479,"form":2},{"id":3,"form":0},{"id":131,"form":0},{"id":815,"form":0},{"id":884,"form":0},{"id":130,"form":0},{"id":858,"form":0},{"id":530,"form":0},{"id":887,"form":0}]},"win":{"waza":[{"id":"323","val":"74.1"},{"id":"90","val":"11.7"},{"id":"59","val":"3.1"},{"id":"196","val":"3.1"},{"id":"484","val":"2.5"},{"id":"56","val":"1.9"},{"id":"57","val":"1.2"},{"id":"127","val":"0.6"},{"id":"58","val":"0.6"},{"id":"340","val":"0.6"}],"pokemon":[{"id":468,"form":0},{"id":778,"form":0},{"id":887,"form":0},{"id":356,"form":0},{"id":812,"form":0},{"id":815,"form":0},{"id":530,"form":0},{"id":727,"form":0},{"id":876,"form":1},{"id":861,"form":0}]}}},"324":{"0":{"temoti":{"waza":[{"id":"284","val":"86.3"},{"id":"257","val":"79.9"},{"id":"182","val":"69.3"},{"id":"76","val":"59.6"},{"id":"414","val":"46.1"},{"id":"281","val":"16.6"},{"id":"776","val":"13.5"},{"id":"53","val":"4.5"},{"id":"499","val":"3.9"},{"id":"807","val":"3.7"}],"tokusei":[{"id":"70","val":"99.9"},{"id":"73","val":"0.0"},{"id":"75","val":"0.0"}],"motimono":[{"id":"249","val":"54.0"},{"id":"297","val":"11.8"},{"id":"640","val":"4.7"},{"id":"158","val":"4.4"},{"id":"275","val":"3.8"},{"id":"217","val":"2.8"},{"id":"284","val":"2.5"},{"id":"159","val":"1.8"},{"id":"270","val":"1.7"},{"id":"1119","val":"1.5"}],"pokemon":[{"id":3,"form":0},{"id":356,"form":0},{"id":6,"form":0},{"id":464,"form":0},{"id":876,"form":1},{"id":858,"form":0},{"id":468,"form":0},{"id":248,"form":0},{"id":815,"form":0},{"id":534,"form":0}]},"lose":{"waza":[{"id":"157","val":"12.5"},{"id":"56","val":"5.7"},{"id":"667","val":"5.1"},{"id":"89","val":"4.4"},{"id":"797","val":"3.9"},{"id":"414","val":"3.9"},{"id":"403","val":"3.8"},{"id":"304","val":"3.5"},{"id":"308","val":"2.7"},{"id":"330","val":"2.6"}],"pokemon":[{"id":248,"form":0},{"id":730,"form":0},{"id":530,"form":0},{"id":468,"form":0},{"id":131,"form":0},{"id":887,"form":0},{"id":464,"form":0},{"id":815,"form":0},{"id":350,"form":0},{"id":858,"form":0}]},"win":{"waza":[{"id":"284","val":"53.7"},{"id":"257","val":"29.2"},{"id":"414","val":"5.5"},{"id":"76","val":"4.8"},{"id":"776","val":"2.6"},{"id":"807","val":"1.3"},{"id":"53","val":"0.9"},{"id":"315","val":"0.8"},{"id":"436","val":"0.3"},{"id":"188","val":"0.2"}],"pokemon":[{"id":547,"form":0},{"id":815,"form":0},{"id":812,"form":0},{"id":468,"form":0},{"id":356,"form":0},{"id":530,"form":0},{"id":876,"form":1},{"id":887,"form":0},{"id":778,"form":0},{"id":727,"form":0}]}}},"328":{"0":{"temoti":{"waza":[{"id":"276","val":"59.1"},{"id":"89","val":"59.1"},{"id":"364","val":"59.1"},{"id":"660","val":"59.1"},{"id":"213","val":"40.9"},{"id":"90","val":"40.9"},{"id":"242","val":"27.3"},{"id":"523","val":"18.2"},{"id":"91","val":"13.6"},{"id":"182","val":"13.6"}],"tokusei":[{"id":"71","val":"100.0"}],"motimono":[{"id":"275","val":"83.3"},{"id":"538","val":"16.7"}],"pokemon":[{"id":468,"form":0},{"id":727,"form":0},{"id":350,"form":0},{"id":861,"form":0},{"id":635,"form":0},{"id":464,"form":0},{"id":851,"form":0},{"id":556,"form":0},{"id":887,"form":0},{"id":678,"form":0}]},"lose":{"waza":[{"id":"394","val":"12.5"},{"id":"399","val":"12.5"},{"id":"284","val":"12.5"},{"id":"605","val":"12.5"},{"id":"452","val":"12.5"},{"id":"276","val":"12.5"},{"id":"246","val":"12.5"},{"id":"56","val":"12.5"}],"pokemon":[{"id":324,"form":0},{"id":272,"form":0},{"id":839,"form":0},{"id":812,"form":0},{"id":727,"form":0},{"id":468,"form":0},{"id":687,"form":0},{"id":479,"form":2}]},"win":{"waza":[{"id":"90","val":"100.0"}],"pokemon":[{"id":26,"form":0},{"id":547,"form":0},{"id":350,"form":0}]}}},"330":{"0":{"temoti":{"waza":[{"id":"89","val":"52.5"},{"id":"157","val":"44.7"},{"id":"414","val":"41.6"},{"id":"434","val":"36.4"},{"id":"784","val":"24.7"},{"id":"182","val":"23.8"},{"id":"337","val":"19.8"},{"id":"276","val":"16.0"},{"id":"202","val":"12.5"},{"id":"369","val":"11.4"}],"tokusei":[{"id":"26","val":"100.0"}],"motimono":[{"id":"270","val":"32.5"},{"id":"287","val":"16.6"},{"id":"220","val":"11.2"},{"id":"268","val":"11.2"},{"id":"275","val":"6.4"},{"id":"297","val":"5.2"},{"id":"639","val":"4.3"},{"id":"640","val":"4.2"},{"id":"266","val":"1.9"},{"id":"686","val":"1.4"}],"pokemon":[{"id":468,"form":0},{"id":547,"form":0},{"id":350,"form":0},{"id":131,"form":0},{"id":700,"form":0},{"id":727,"form":0},{"id":778,"form":0},{"id":479,"form":2},{"id":849,"form":1},{"id":248,"form":0}]},"lose":{"waza":[{"id":"605","val":"11.3"},{"id":"585","val":"7.9"},{"id":"442","val":"4.5"},{"id":"58","val":"3.9"},{"id":"434","val":"3.6"},{"id":"59","val":"2.8"},{"id":"751","val":"2.8"},{"id":"583","val":"2.5"},{"id":"337","val":"2.3"},{"id":"389","val":"2.3"}],"pokemon":[{"id":468,"form":0},{"id":887,"form":0},{"id":815,"form":0},{"id":730,"form":0},{"id":547,"form":0},{"id":131,"form":0},{"id":812,"form":0},{"id":248,"form":0},{"id":534,"form":0},{"id":530,"form":0}]},"win":{"waza":[{"id":"89","val":"31.5"},{"id":"414","val":"16.6"},{"id":"157","val":"13.1"},{"id":"434","val":"6.4"},{"id":"200","val":"3.8"},{"id":"337","val":"3.6"},{"id":"19","val":"2.4"},{"id":"257","val":"2.2"},{"id":"784","val":"1.9"},{"id":"276","val":"1.7"}],"pokemon":[{"id":815,"form":0},{"id":530,"form":0},{"id":248,"form":0},{"id":468,"form":0},{"id":547,"form":0},{"id":887,"form":0},{"id":324,"form":0},{"id":839,"form":0},{"id":876,"form":1},{"id":727,"form":0}]}}},"337":{"0":{"temoti":{"waza":[{"id":"408","val":"89.5"},{"id":"433","val":"50.2"},{"id":"414","val":"48.6"},{"id":"502","val":"43.1"},{"id":"182","val":"41.5"},{"id":"523","val":"41.2"},{"id":"473","val":"40.3"},{"id":"585","val":"11.7"},{"id":"800","val":"9.8"},{"id":"247","val":"5.2"}],"tokusei":[{"id":"26","val":"100.0"}],"motimono":[{"id":"275","val":"37.7"},{"id":"639","val":"37.7"},{"id":"271","val":"12.0"},{"id":"287","val":"4.6"},{"id":"159","val":"2.3"},{"id":"270","val":"2.3"},{"id":"219","val":"1.7"},{"id":"640","val":"1.1"},{"id":"238","val":"0.6"}],"pokemon":[{"id":9,"form":0},{"id":26,"form":0},{"id":858,"form":0},{"id":876,"form":1},{"id":812,"form":0},{"id":350,"form":0},{"id":828,"form":0},{"id":820,"form":0},{"id":248,"form":0},{"id":748,"form":0}]},"lose":{"waza":[{"id":"442","val":"12.9"},{"id":"282","val":"3.8"},{"id":"605","val":"3.8"},{"id":"663","val":"3.8"},{"id":"76","val":"3.0"},{"id":"157","val":"3.0"},{"id":"751","val":"3.0"},{"id":"242","val":"3.0"},{"id":"56","val":"3.0"},{"id":"389","val":"2.3"}],"pokemon":[{"id":815,"form":0},{"id":248,"form":0},{"id":812,"form":0},{"id":131,"form":0},{"id":887,"form":0},{"id":468,"form":0},{"id":530,"form":0},{"id":727,"form":0},{"id":750,"form":0},{"id":547,"form":0}]},"win":{"waza":[{"id":"408","val":"50.0"},{"id":"473","val":"17.6"},{"id":"414","val":"16.7"},{"id":"800","val":"7.8"},{"id":"585","val":"2.9"},{"id":"523","val":"2.9"},{"id":"94","val":"1.0"},{"id":"500","val":"1.0"}],"pokemon":[{"id":468,"form":0},{"id":3,"form":0},{"id":815,"form":0},{"id":727,"form":0},{"id":59,"form":0},{"id":324,"form":0},{"id":547,"form":0},{"id":38,"form":0},{"id":6,"form":0},{"id":130,"form":0}]}}},"338":{"0":{"temoti":{"waza":[{"id":"157","val":"71.0"},{"id":"397","val":"46.0"},{"id":"322","val":"46.0"},{"id":"500","val":"45.0"},{"id":"433","val":"28.0"},{"id":"428","val":"27.0"},{"id":"394","val":"24.0"},{"id":"261","val":"21.0"},{"id":"270","val":"18.0"},{"id":"89","val":"16.0"}],"tokusei":[{"id":"26","val":"100.0"}],"motimono":[{"id":"639","val":"60.9"},{"id":"275","val":"12.5"},{"id":"219","val":"12.5"},{"id":"564","val":"4.7"},{"id":"270","val":"3.1"},{"id":"265","val":"3.1"},{"id":"158","val":"3.1"}],"pokemon":[{"id":700,"form":0},{"id":9,"form":0},{"id":743,"form":0},{"id":178,"form":0},{"id":765,"form":0},{"id":730,"form":0},{"id":248,"form":0},{"id":727,"form":0},{"id":869,"form":0},{"id":887,"form":0}]},"lose":{"waza":[{"id":"247","val":"9.3"},{"id":"56","val":"7.0"},{"id":"503","val":"4.7"},{"id":"242","val":"4.7"},{"id":"412","val":"4.7"},{"id":"430","val":"4.7"},{"id":"89","val":"4.7"},{"id":"76","val":"4.7"},{"id":"566","val":"4.7"},{"id":"803","val":"4.7"}],"pokemon":[{"id":464,"form":0},{"id":887,"form":0},{"id":812,"form":0},{"id":350,"form":0},{"id":884,"form":0},{"id":839,"form":0},{"id":248,"form":0},{"id":131,"form":0},{"id":3,"form":0},{"id":479,"form":2}]},"win":{"waza":[{"id":"157","val":"63.2"},{"id":"500","val":"15.8"},{"id":"394","val":"10.5"},{"id":"83","val":"5.3"},{"id":"442","val":"5.3"}],"pokemon":[{"id":547,"form":0},{"id":131,"form":0},{"id":6,"form":0},{"id":3,"form":0},{"id":876,"form":1},{"id":38,"form":1},{"id":815,"form":0},{"id":876,"form":0},{"id":38,"form":0},{"id":823,"form":0}]}}},"339":{"0":{"temoti":{"waza":[{"id":"90","val":"100.0"},{"id":"214","val":"100.0"},{"id":"503","val":"100.0"},{"id":"156","val":"100.0"}],"tokusei":[],"motimono":[],"pokemon":[{"id":547,"form":0},{"id":884,"form":0},{"id":876,"form":0},{"id":448,"form":0},{"id":882,"form":0}]},"lose":{"waza":[],"pokemon":[]},"win":{"waza":[],"pokemon":[]}}},"340":{"0":{"temoti":{"waza":[{"id":"349","val":"75.8"},{"id":"89","val":"63.6"},{"id":"127","val":"42.4"},{"id":"182","val":"39.4"},{"id":"710","val":"33.3"},{"id":"56","val":"21.2"},{"id":"156","val":"21.2"},{"id":"330","val":"21.2"},{"id":"414","val":"21.2"},{"id":"340","val":"15.2"}],"tokusei":[{"id":"12","val":"52.9"},{"id":"93","val":"29.4"},{"id":"107","val":"17.6"}],"motimono":[{"id":"163","val":"23.5"},{"id":"270","val":"23.5"},{"id":"268","val":"17.6"},{"id":"639","val":"17.6"},{"id":"187","val":"5.9"},{"id":"157","val":"5.9"},{"id":"650","val":"5.9"}],"pokemon":[{"id":547,"form":0},{"id":887,"form":0},{"id":815,"form":0},{"id":135,"form":0},{"id":884,"form":0},{"id":869,"form":0},{"id":871,"form":0},{"id":279,"form":0},{"id":847,"form":0},{"id":625,"form":0}]},"lose":{"waza":[{"id":"434","val":"20.0"},{"id":"452","val":"10.0"},{"id":"412","val":"10.0"},{"id":"667","val":"10.0"},{"id":"58","val":"10.0"},{"id":"789","val":"10.0"},{"id":"573","val":"10.0"},{"id":"442","val":"10.0"},{"id":"751","val":"10.0"}],"pokemon":[{"id":884,"form":0},{"id":609,"form":0},{"id":778,"form":0},{"id":131,"form":0},{"id":887,"form":0},{"id":530,"form":0},{"id":861,"form":0},{"id":450,"form":0},{"id":9,"form":0}]},"win":{"waza":[{"id":"89","val":"70.0"},{"id":"710","val":"10.0"},{"id":"127","val":"10.0"},{"id":"340","val":"10.0"}],"pokemon":[{"id":59,"form":0},{"id":876,"form":1},{"id":530,"form":0},{"id":632,"form":0},{"id":884,"form":0},{"id":887,"form":0},{"id":464,"form":0},{"id":110,"form":1},{"id":38,"form":1},{"id":248,"form":0}]}}},"341":{"0":{"temoti":{"waza":[{"id":"453","val":"100.0"},{"id":"283","val":"100.0"},{"id":"282","val":"100.0"},{"id":"152","val":"100.0"}],"tokusei":[{"id":"91","val":"100.0"}],"motimono":[{"id":"275","val":"100.0"}],"pokemon":[{"id":464,"form":0},{"id":534,"form":0},{"id":876,"form":1},{"id":356,"form":0},{"id":598,"form":0}]},"lose":{"waza":[],"pokemon":[]},"win":{"waza":[],"pokemon":[]}}},"342":{"0":{"temoti":{"waza":[{"id":"282","val":"95.8"},{"id":"453","val":"82.8"},{"id":"152","val":"68.4"},{"id":"182","val":"44.9"},{"id":"370","val":"30.9"},{"id":"710","val":"22.8"},{"id":"280","val":"8.6"},{"id":"269","val":"8.3"},{"id":"14","val":"7.9"},{"id":"242","val":"6.6"}],"tokusei":[{"id":"91","val":"99.0"},{"id":"52","val":"1.0"}],"motimono":[{"id":"270","val":"33.5"},{"id":"275","val":"23.9"},{"id":"220","val":"20.1"},{"id":"240","val":"4.7"},{"id":"268","val":"2.9"},{"id":"278","val":"2.6"},{"id":"266","val":"2.3"},{"id":"287","val":"1.9"},{"id":"640","val":"1.3"},{"id":"639","val":"1.3"}],"pokemon":[{"id":468,"form":0},{"id":547,"form":0},{"id":815,"form":0},{"id":887,"form":0},{"id":858,"form":0},{"id":812,"form":0},{"id":356,"form":0},{"id":530,"form":0},{"id":464,"form":0},{"id":302,"form":0}]},"lose":{"waza":[{"id":"605","val":"12.4"},{"id":"85","val":"7.6"},{"id":"585","val":"7.5"},{"id":"136","val":"4.4"},{"id":"76","val":"3.0"},{"id":"276","val":"2.9"},{"id":"438","val":"2.8"},{"id":"304","val":"2.5"},{"id":"157","val":"2.5"},{"id":"412","val":"2.5"}],"pokemon":[{"id":468,"form":0},{"id":547,"form":0},{"id":815,"form":0},{"id":730,"form":0},{"id":131,"form":0},{"id":812,"form":0},{"id":248,"form":0},{"id":887,"form":0},{"id":534,"form":0},{"id":479,"form":2}]},"win":{"waza":[{"id":"282","val":"42.2"},{"id":"453","val":"26.9"},{"id":"152","val":"20.4"},{"id":"710","val":"4.7"},{"id":"370","val":"2.1"},{"id":"242","val":"1.1"},{"id":"157","val":"0.5"},{"id":"808","val":"0.5"},{"id":"280","val":"0.4"},{"id":"399","val":"0.4"}],"pokemon":[{"id":356,"form":0},{"id":815,"form":0},{"id":887,"form":0},{"id":876,"form":1},{"id":468,"form":0},{"id":530,"form":0},{"id":248,"form":0},{"id":727,"form":0},{"id":59,"form":0},{"id":839,"form":0}]}}},"344":{"0":{"temoti":{"waza":[{"id":"433","val":"85.9"},{"id":"502","val":"67.6"},{"id":"286","val":"66.5"},{"id":"414","val":"56.1"},{"id":"815","val":"19.3"},{"id":"776","val":"14.8"},{"id":"94","val":"12.8"},{"id":"322","val":"9.2"},{"id":"182","val":"7.0"},{"id":"797","val":"6.6"}],"tokusei":[{"id":"26","val":"100.0"}],"motimono":[{"id":"275","val":"20.5"},{"id":"158","val":"17.7"},{"id":"237","val":"15.8"},{"id":"639","val":"9.5"},{"id":"650","val":"7.6"},{"id":"234","val":"7.3"},{"id":"198","val":"6.6"},{"id":"882","val":"3.8"},{"id":"196","val":"2.8"},{"id":"270","val":"1.6"}],"pokemon":[{"id":815,"form":0},{"id":468,"form":0},{"id":555,"form":2},{"id":479,"form":2},{"id":547,"form":0},{"id":3,"form":0},{"id":59,"form":0},{"id":727,"form":0},{"id":130,"form":0},{"id":887,"form":0}]},"lose":{"waza":[{"id":"605","val":"6.2"},{"id":"242","val":"5.2"},{"id":"389","val":"3.8"},{"id":"566","val":"3.8"},{"id":"247","val":"3.3"},{"id":"304","val":"2.9"},{"id":"257","val":"2.9"},{"id":"284","val":"2.9"},{"id":"452","val":"2.9"},{"id":"442","val":"2.9"}],"pokemon":[{"id":248,"form":0},{"id":887,"form":0},{"id":730,"form":0},{"id":468,"form":0},{"id":815,"form":0},{"id":812,"form":0},{"id":778,"form":0},{"id":324,"form":0},{"id":727,"form":0},{"id":3,"form":0}]},"win":{"waza":[{"id":"414","val":"58.5"},{"id":"815","val":"9.8"},{"id":"776","val":"9.8"},{"id":"94","val":"8.5"},{"id":"529","val":"3.7"},{"id":"326","val":"2.4"},{"id":"523","val":"2.4"},{"id":"500","val":"1.2"},{"id":"58","val":"1.2"},{"id":"153","val":"1.2"}],"pokemon":[{"id":324,"form":0},{"id":876,"form":1},{"id":356,"form":0},{"id":530,"form":0},{"id":730,"form":0},{"id":248,"form":0},{"id":815,"form":0},{"id":547,"form":0},{"id":727,"form":0},{"id":858,"form":0}]}}},"349":{"0":{"temoti":{"waza":[{"id":"59","val":"96.2"},{"id":"113","val":"96.2"},{"id":"58","val":"96.2"},{"id":"95","val":"96.2"},{"id":"150","val":"3.8"}],"tokusei":[{"id":"12","val":"100.0"}],"motimono":[{"id":"275","val":"92.3"},{"id":"538","val":"7.7"}],"pokemon":[{"id":129,"form":0},{"id":143,"form":0},{"id":324,"form":0},{"id":79,"form":1},{"id":781,"form":0},{"id":818,"form":0},{"id":208,"form":0},{"id":534,"form":0},{"id":882,"form":0},{"id":832,"form":0}]},"lose":{"waza":[{"id":"9","val":"33.3"},{"id":"94","val":"33.3"},{"id":"542","val":"33.3"}],"pokemon":[{"id":660,"form":0},{"id":279,"form":0},{"id":876,"form":0}]},"win":{"waza":[],"pokemon":[]}}},"350":{"0":{"temoti":{"waza":[{"id":"330","val":"81.5"},{"id":"105","val":"59.8"},{"id":"95","val":"42.7"},{"id":"489","val":"41.2"},{"id":"58","val":"36.5"},{"id":"341","val":"25.9"},{"id":"182","val":"25.4"},{"id":"59","val":"17.3"},{"id":"196","val":"17.0"},{"id":"503","val":"15.8"}],"tokusei":[{"id":"172","val":"98.5"},{"id":"63","val":"1.4"},{"id":"56","val":"0.1"}],"motimono":[{"id":"234","val":"23.5"},{"id":"640","val":"12.9"},{"id":"270","val":"11.6"},{"id":"1121","val":"11.0"},{"id":"158","val":"9.1"},{"id":"160","val":"7.0"},{"id":"297","val":"4.1"},{"id":"884","val":"3.1"},{"id":"639","val":"3.0"},{"id":"265","val":"2.0"}],"pokemon":[{"id":815,"form":0},{"id":468,"form":0},{"id":547,"form":0},{"id":812,"form":0},{"id":248,"form":0},{"id":887,"form":0},{"id":530,"form":0},{"id":59,"form":0},{"id":727,"form":0},{"id":884,"form":0}]},"lose":{"waza":[{"id":"85","val":"8.5"},{"id":"452","val":"6.2"},{"id":"438","val":"4.6"},{"id":"157","val":"4.6"},{"id":"412","val":"4.2"},{"id":"605","val":"3.4"},{"id":"9","val":"2.8"},{"id":"76","val":"2.6"},{"id":"667","val":"2.6"},{"id":"340","val":"2.5"}],"pokemon":[{"id":812,"form":0},{"id":815,"form":0},{"id":248,"form":0},{"id":887,"form":0},{"id":479,"form":2},{"id":730,"form":0},{"id":468,"form":0},{"id":530,"form":0},{"id":3,"form":0},{"id":534,"form":0}]},"win":{"waza":[{"id":"330","val":"55.7"},{"id":"58","val":"13.0"},{"id":"503","val":"8.6"},{"id":"59","val":"7.8"},{"id":"341","val":"6.0"},{"id":"196","val":"3.4"},{"id":"56","val":"3.2"},{"id":"57","val":"0.7"},{"id":"406","val":"0.6"},{"id":"574","val":"0.4"}],"pokemon":[{"id":468,"form":0},{"id":815,"form":0},{"id":547,"form":0},{"id":530,"form":0},{"id":727,"form":0},{"id":887,"form":0},{"id":59,"form":0},{"id":248,"form":0},{"id":356,"form":0},{"id":464,"form":0}]}}},"355":{"0":{"temoti":{"waza":[{"id":"270","val":"100.0"},{"id":"425","val":"100.0"},{"id":"433","val":"100.0"},{"id":"502","val":"78.6"},{"id":"101","val":"21.4"}],"tokusei":[{"id":"119","val":"100.0"}],"motimono":[{"id":"538","val":"100.0"}],"pokemon":[{"id":855,"form":0},{"id":448,"form":0},{"id":876,"form":1},{"id":887,"form":0},{"id":59,"form":0}]},"lose":{"waza":[{"id":"394","val":"12.5"},{"id":"420","val":"12.5"},{"id":"786","val":"12.5"},{"id":"399","val":"12.5"},{"id":"247","val":"12.5"},{"id":"304","val":"12.5"},{"id":"605","val":"12.5"},{"id":"59","val":"12.5"}],"pokemon":[{"id":468,"form":0},{"id":849,"form":0},{"id":884,"form":0},{"id":350,"form":0},{"id":730,"form":0},{"id":471,"form":0},{"id":839,"form":0},{"id":131,"form":0}]},"win":{"waza":[{"id":"425","val":"100.0"}],"pokemon":[{"id":576,"form":0},{"id":530,"form":0}]}}},"356":{"0":{"temoti":{"waza":[{"id":"433","val":"97.3"},{"id":"101","val":"89.0"},{"id":"220","val":"60.2"},{"id":"502","val":"43.9"},{"id":"523","val":"23.9"},{"id":"261","val":"21.5"},{"id":"270","val":"17.0"},{"id":"114","val":"14.8"},{"id":"425","val":"11.0"},{"id":"280","val":"5.8"}],"tokusei":[{"id":"119","val":"92.1"},{"id":"46","val":"7.9"}],"motimono":[{"id":"538","val":"99.6"},{"id":"219","val":"0.2"},{"id":"229","val":"0.0"},{"id":"541","val":"0.0"},{"id":"206","val":"0.0"},{"id":"234","val":"0.0"},{"id":"162","val":"0.0"},{"id":"275","val":"0.0"},{"id":"198","val":"0.0"},{"id":"196","val":"0.0"}],"pokemon":[{"id":468,"form":0},{"id":730,"form":0},{"id":248,"form":0},{"id":464,"form":0},{"id":324,"form":0},{"id":727,"form":0},{"id":887,"form":0},{"id":815,"form":0},{"id":534,"form":0},{"id":876,"form":1}]},"lose":{"waza":[{"id":"566","val":"5.3"},{"id":"242","val":"5.3"},{"id":"389","val":"5.1"},{"id":"399","val":"4.5"},{"id":"247","val":"4.5"},{"id":"605","val":"4.2"},{"id":"257","val":"3.2"},{"id":"101","val":"3.1"},{"id":"442","val":"2.8"},{"id":"157","val":"2.8"}],"pokemon":[{"id":248,"form":0},{"id":815,"form":0},{"id":887,"form":0},{"id":730,"form":0},{"id":812,"form":0},{"id":468,"form":0},{"id":884,"form":0},{"id":356,"form":0},{"id":727,"form":0},{"id":324,"form":0}]},"win":{"waza":[{"id":"101","val":"88.8"},{"id":"425","val":"5.7"},{"id":"523","val":"3.3"},{"id":"280","val":"1.1"},{"id":"89","val":"0.2"},{"id":"317","val":"0.2"},{"id":"506","val":"0.1"},{"id":"809","val":"0.1"},{"id":"247","val":"0.1"},{"id":"325","val":"0.1"}],"pokemon":[{"id":547,"form":0},{"id":468,"form":0},{"id":356,"form":0},{"id":815,"form":0},{"id":530,"form":0},{"id":812,"form":0},{"id":730,"form":0},{"id":131,"form":0},{"id":887,"form":0},{"id":534,"form":0}]}}},"362":{"0":{"temoti":{"waza":[{"id":"573","val":"70.3"},{"id":"182","val":"69.5"},{"id":"164","val":"67.2"},{"id":"524","val":"42.2"},{"id":"247","val":"21.9"},{"id":"556","val":"14.1"},{"id":"196","val":"13.3"},{"id":"89","val":"12.5"},{"id":"420","val":"10.2"},{"id":"44","val":"10.2"}],"tokusei":[{"id":"141","val":"75.3"},{"id":"39","val":"21.6"},{"id":"115","val":"3.1"}],"motimono":[{"id":"234","val":"58.8"},{"id":"287","val":"10.3"},{"id":"275","val":"5.2"},{"id":"160","val":"4.1"},{"id":"649","val":"3.1"},{"id":"884","val":"2.1"},{"id":"1119","val":"2.1"},{"id":"650","val":"1.0"}],"pokemon":[{"id":282,"form":0},{"id":823,"form":0},{"id":839,"form":0},{"id":530,"form":0},{"id":479,"form":2},{"id":849,"form":0},{"id":818,"form":0},{"id":468,"form":0},{"id":861,"form":0},{"id":38,"form":1}]},"lose":{"waza":[{"id":"442","val":"11.6"},{"id":"780","val":"9.3"},{"id":"257","val":"7.0"},{"id":"360","val":"4.7"},{"id":"304","val":"4.7"},{"id":"394","val":"4.7"},{"id":"56","val":"4.7"},{"id":"157","val":"4.7"},{"id":"76","val":"2.3"},{"id":"413","val":"2.3"}],"pokemon":[{"id":815,"form":0},{"id":887,"form":0},{"id":324,"form":0},{"id":468,"form":0},{"id":609,"form":0},{"id":700,"form":0},{"id":530,"form":0},{"id":727,"form":0},{"id":479,"form":2},{"id":598,"form":0}]},"win":{"waza":[{"id":"573","val":"58.3"},{"id":"247","val":"12.5"},{"id":"242","val":"8.3"},{"id":"420","val":"8.3"},{"id":"524","val":"4.2"},{"id":"89","val":"4.2"},{"id":"556","val":"4.2"}],"pokemon":[{"id":812,"form":0},{"id":468,"form":0},{"id":858,"form":0},{"id":547,"form":0},{"id":701,"form":0},{"id":130,"form":0},{"id":746,"form":0},{"id":635,"form":0},{"id":479,"form":2},{"id":248,"form":0}]}}}}